django_leaflet_storage-0.8.2.dist-info/DESCRIPTION.rst
django_leaflet_storage-0.8.2.dist-info/METADATA
django_leaflet_storage-0.8.2.dist-info/RECORD
django_leaflet_storage-0.8.2.dist-info/WHEEL
django_leaflet_storage-0.8.2.dist-info/metadata.json
django_leaflet_storage-0.8.2.dist-info/top_level.txt
leaflet_storage/__init__.py
leaflet_storage/admin.py
leaflet_storage/decorators.py
leaflet_storage/fields.py
leaflet_storage/forms.py
leaflet_storage/managers.py
leaflet_storage/models.py
leaflet_storage/urls.py
leaflet_storage/utils.py
leaflet_storage/views.py
leaflet_storage/locale/am_ET/LC_MESSAGES/django.mo
leaflet_storage/locale/am_ET/LC_MESSAGES/django.po
leaflet_storage/locale/bg/LC_MESSAGES/django.mo
leaflet_storage/locale/bg/LC_MESSAGES/django.po
leaflet_storage/locale/ca/LC_MESSAGES/django.mo
leaflet_storage/locale/ca/LC_MESSAGES/django.po
leaflet_storage/locale/cs_CZ/LC_MESSAGES/django.mo
leaflet_storage/locale/cs_CZ/LC_MESSAGES/django.po
leaflet_storage/locale/da/LC_MESSAGES/django.mo
leaflet_storage/locale/da/LC_MESSAGES/django.po
leaflet_storage/locale/de/LC_MESSAGES/django.mo
leaflet_storage/locale/de/LC_MESSAGES/django.po
leaflet_storage/locale/en/LC_MESSAGES/django.mo
leaflet_storage/locale/en/LC_MESSAGES/django.po
leaflet_storage/locale/es/LC_MESSAGES/django.mo
leaflet_storage/locale/es/LC_MESSAGES/django.po
leaflet_storage/locale/fi/LC_MESSAGES/django.mo
leaflet_storage/locale/fi/LC_MESSAGES/django.po
leaflet_storage/locale/fr/LC_MESSAGES/django.mo
leaflet_storage/locale/fr/LC_MESSAGES/django.po
leaflet_storage/locale/it/LC_MESSAGES/django.mo
leaflet_storage/locale/it/LC_MESSAGES/django.po
leaflet_storage/locale/ja/LC_MESSAGES/django.mo
leaflet_storage/locale/ja/LC_MESSAGES/django.po
leaflet_storage/locale/lt/LC_MESSAGES/django.mo
leaflet_storage/locale/lt/LC_MESSAGES/django.po
leaflet_storage/locale/nl/LC_MESSAGES/django.mo
leaflet_storage/locale/nl/LC_MESSAGES/django.po
leaflet_storage/locale/pl/LC_MESSAGES/django.mo
leaflet_storage/locale/pl/LC_MESSAGES/django.po
leaflet_storage/locale/pt/LC_MESSAGES/django.mo
leaflet_storage/locale/pt/LC_MESSAGES/django.po
leaflet_storage/locale/ru/LC_MESSAGES/django.mo
leaflet_storage/locale/ru/LC_MESSAGES/django.po
