Metadata-Version: 2.0
Name: django-leaflet-storage
Version: 0.8.2
Summary: Create collaborative maps on top of Geodjango and Leaflet.
Home-page: https://github.com/umap-project/django-leaflet-storage
Author: Yohan Boniface
Author-email: yb@enix.fr
License: UNKNOWN
Download-URL: https://github.com/yohanboniface/django-leaflet-storage/downloads
Keywords: django leaflet geodjango
Platform: any
Classifier: Development Status :: 3 - Alpha
Classifier: Environment :: Web Environment
Classifier: Intended Audience :: Developers
Classifier: Operating System :: OS Independent
Classifier: Topic :: Software Development :: Libraries :: Python Modules
Classifier: Programming Language :: Python
